nomad_measurements/__init__.py
nomad_measurements/general.py
nomad_measurements/utils.py
nomad_measurements/mapping/__init__.py
nomad_measurements/mapping/schema.py
nomad_measurements/quantumdesign/__init__.py
nomad_measurements/quantumdesign/parser.py
nomad_measurements/quantumdesign/qddatastruct.py
nomad_measurements/quantumdesign/qdfunctions.py
nomad_measurements/quantumdesign/qdsteps.py
nomad_measurements/quantumdesign/schema.py
nomad_measurements/transmission/__init__.py
nomad_measurements/transmission/parser.py
nomad_measurements/transmission/schema.py
nomad_measurements/xrd/__init__.py
nomad_measurements/xrd/nx.py
nomad_measurements/xrd/parser.py
nomad_measurements/xrd/schema.py
nomad_measurements-1.3.5.dist-info/licenses/LICENSE
nomad_measurements-1.3.5.dist-info/METADATA
nomad_measurements-1.3.5.dist-info/WHEEL
nomad_measurements-1.3.5.dist-info/entry_points.txt
nomad_measurements-1.3.5.dist-info/top_level.txt
nomad_measurements-1.3.5.dist-info/RECORD
