Metadata-Version: 2.4
Name: nomad-measurements
Version: 1.3.5
Summary: A plugin for NOMAD containing base sections for measurements.
Author: Andrea Albino, Sebastian Brückner, Sarthak Kapoor, José A. Márquez, Rubel Mozumder, Hampus Näsström
Author-email: fairmat@physik.hu-berlin.de
Maintainer-email: FAIRmat <fairmat@physik.hu-berlin.de>
License:                                  Apache License
Project-URL: Homepage, https://github.com/FAIRmat-NFDI/nomad-measurements
Project-URL: Bug Tracker, https://github.com/FAIRmat-NFDI/nomad-measurements/issues
Classifier: Intended Audience :: Developers
Classifier: Operating System :: OS Independent
Classifier: Programming Language :: Python
Classifier: Programming Language :: Python :: 3.10
Classifier: Programming Language :: Python :: 3.11
Classifier: Programming Language :: Python :: 3.12
Classifier: License :: OSI Approved :: Apache Software License
Requires-Python: >=3.10
License-File: LICENSE
Requires-Dist: nomad-lab>=1.3.16
Requires-Dist: fairmat-readers-xrd>=0.0.8
Requires-Dist: fairmat-readers-transmission>=0.0.2
Provides-Extra: nexus
Requires-Dist: pynxtools>=0.10.0; extra == "nexus"
Provides-Extra: dev
Requires-Dist: pytest; extra == "dev"
Requires-Dist: ruff; extra == "dev"
Requires-Dist: structlog; extra == "dev"
Requires-Dist: python-logstash>=0.4.6; extra == "dev"
Dynamic: license-file
